atividade24/ula_16bits.vhd
library ieee;
use ieee.std_logic_1164.all;
use ieee.numeric_std.all;

entity ula_16bits is
    port (
        A, B : in  std_logic_vector(15 downto 0);
        M, S1, S0 : in  std_logic;
        F : out std_logic_vector(15 downto 0)
    );
end entity;

architecture arch of ula_16bits is
begin
    process(A, B, M, S1, S0)
        variable soma_sub : signed(15 downto 0);
        variable shift_left, shift_right : std_logic_vector(15 downto 0);
    begin
        if M = '0' then
            -- PARTE ARITMÉTICA (M = 0)
            if S1 = '0' and S0 = '0' then
                -- SOMA: A + B
                F <= std_logic_vector(signed(A) + signed(B));
                
            elsif S1 = '0' and S0 = '1' then
                -- SUBTRAÇÃO: A - B
                F <= std_logic_vector(signed(A) - signed(B));
                
            elsif S1 = '1' and S0 = '0' then
                -- SHIFT LEFT: A << 1
                F <= A(14 downto 0) & '0';
                
            else  -- S1 = '1' and S0 = '1'
                -- SHIFT RIGHT: A >> 1
                F <= '0' & A(15 downto 1);
            end if;
            
        else
            -- PARTE LÓGICA (M = 1)
            if S1 = '0' and S0 = '0' then
                -- AND
                F <= A and B;
                
            elsif S1 = '0' and S0 = '1' then
                -- OR
                F <= A or B;
                
            elsif S1 = '1' and S0 = '0' then
                -- XOR
                F <= A xor B;
                
            else  -- S1 = '1' and S0 = '1'
                -- XNOR
                F <= A xnor B;
            end if;
            
        end if;
    end process;
end architecture;

atividade24/tb_ula_16bits.vhd
library ieee;
use ieee.std_logic_1164.all;
use ieee.numeric_std.all;

entity tb_ula_16bits is
end entity;

architecture sim of tb_ula_16bits is
    signal A, B, F : std_logic_vector(15 downto 0);
    signal M, S1, S0 : std_logic;
begin
    uut: entity work.ula_16bits port map (A, B, M, S1, S0, F);
    
    process
    begin
        -- Valores de teste
        A <= x"0005";  -- 5
        B <= x"0003";  -- 3
        
        M <= '0'; S1 <= '0'; S0 <= '0'; wait for 10 ns;
        
        M <= '0'; S1 <= '0'; S0 <= '1'; wait for 10 ns;
        
        M <= '0'; S1 <= '1'; S0 <= '0'; wait for 10 ns;
        
        M <= '0'; S1 <= '1'; S0 <= '1'; wait for 10 ns;
        
        M <= '1'; S1 <= '0'; S0 <= '0'; wait for 10 ns;
        
        M <= '1'; S1 <= '0'; S0 <= '1'; wait for 10 ns;
        
        M <= '1'; S1 <= '1'; S0 <= '0'; wait for 10 ns;
        
        M <= '1'; S1 <= '1'; S0 <= '1'; wait for 10 ns;
        
        wait;
    end process;
end architecture;

atividade24/onda_ula.vcd
$date
  Tue May 26 13:16:15 2026
$end
$version
  GHDL v0
$end
$timescale
  1 fs
$end
$scope module standard $end
$upscope $end
$scope module std_logic_1164 $end
$upscope $end
$scope module numeric_std $end
$upscope $end
$scope module tb_ula_16bits $end
$var reg 16 ! a[15:0] $end
$var reg 16 " b[15:0] $end
$var reg 16 # f[15:0] $end
$var reg 1 $ m $end
$var reg 1 % s1 $end
$var reg 1 & s0 $end
$scope module uut $end
$var reg 16 ' a[15:0] $end
$var reg 16 ( b[15:0] $end
$var reg 1 ) m $end
$var reg 1 * s1 $end
$var reg 1 + s0 $end
$var reg 16 , f[15:0] $end
$upscope $end
$upscope $end
$enddefinitions $end
#0
b0000000000000101 !
b0000000000000011 "
b0000000000001000 #
0$
0%
0&
b0000000000000101 '
b0000000000000011 (
0)
0*
0+
b0000000000001000 ,
#10000000
b0000000000000010 #
1&
1+
b0000000000000010 ,
#20000000
b0000000000001010 #
1%
0&
1*
0+
b0000000000001010 ,
#30000000
b0000000000000010 #
1&
1+
b0000000000000010 ,
#40000000
b0000000000000001 #
1$
0%
0&
1)
0*
0+
b0000000000000001 ,
#50000000
b0000000000000111 #
1&
1+
b0000000000000111 ,
#60000000
b0000000000000110 #
1%
0&
1*
0+
b0000000000000110 ,
#70000000
b1111111111111001 #
1&
1+
b1111111111111001 ,
